django_users_login
