Metadata-Version: 1.0
Name: django-users-login
Version: 0.1.2
Summary: Extension to manage users in django application.
Home-page: http://bitbucket.org/quein/django-users-login/
Author: Geraldo Andrade
Author-email: geraldo@geraldoandrade.com
License: MIT
Download-URL: https://bitbucket.org/quein/django-users-login/get/master.zip
Platform: any
Classifier: Development Status :: 3 - Alpha
Classifier: Environment :: Web Environment
Classifier: Intended Audience :: Developers
Classifier: License :: OSI Approved :: MIT License
Classifier: Operating System :: OS Independent
Classifier: Programming Language :: Python
Classifier: Topic :: Internet :: WWW/HTTP :: Dynamic Content
Classifier: Topic :: Software Development :: Libraries :: Python Modules
